modelutils/__init__.py
modelutils/caffe/__init__.py
modelutils/caffe/dump.py
modelutils/caffe/get_data.py
modelutils/caffe/load.py
modelutils/caffe/run_model.py
modelutils/caffe/summarize.py
modelutils/commands/__init__.py
modelutils/commands/diff.py
modelutils/commands/dump.py
modelutils/commands/get.py
modelutils/commands/get_data.py
modelutils/commands/image.py
modelutils/commands/json.py
modelutils/commands/load.py
modelutils/commands/max.py
modelutils/commands/print.py
modelutils/commands/run.py
modelutils/commands/set_data.py
modelutils/commands/summarize.py
modelutils/commands/transpose.py
modelutils/commands/zeros.py
modelutils/common/__init__.py
modelutils/common/draw_bounding_boxes.py
modelutils/common/model.py
modelutils/common/summarizer.py
modelutils/common/utils.py
modelutils/coreml/__init__.py
modelutils/coreml/convert_fp32_to_fp16.py
modelutils/coreml/dump.py
modelutils/onnx/__init__.py
modelutils/onnx/add_cast_for_op.py
modelutils/onnx/add_cast_op.py
modelutils/onnx/add_mean_subtraction.py
modelutils/onnx/add_output.py
modelutils/onnx/benchmark.py
modelutils/onnx/cat_graph.py
modelutils/onnx/check.py
modelutils/onnx/convert_fp32_to_fp16.py
modelutils/onnx/cut_graph.py
modelutils/onnx/dump.py
modelutils/onnx/get_data.py
modelutils/onnx/load.py
modelutils/onnx/optimize.py
modelutils/onnx/run_model.py
modelutils/onnx/set_data.py
modelutils/onnx/summarize.py
modelutils/onnx/weights_hash.py
modelutils/openvino/__init__.py
modelutils/openvino/add_const.py
modelutils/openvino/randomize_weights.py
modelutils/openvino/run_model.py
modelutils/openvino/summarize.py
modelutils/openvino/update_const.py
modelutils/openvino/weights_hash.py
modelutils/pytorch/__init__.py
modelutils/pytorch/get_data.py
modelutils/pytorch/rename_weights.py
modelutils/tensorflow/__init__.py
modelutils/tensorflow/benchmark.py
modelutils/tensorflow/copy_weights_to_tensorflowjs.py
modelutils/tensorflow/dump.py
modelutils/tensorflow/get_data.py
modelutils/tensorflow/load.py
modelutils-0.1.2.dist-info/LICENSE
modelutils-0.1.2.dist-info/METADATA
modelutils-0.1.2.dist-info/WHEEL
modelutils-0.1.2.dist-info/entry_points.txt
modelutils-0.1.2.dist-info/top_level.txt
modelutils-0.1.2.dist-info/RECORD
